Metadata-Version: 1.0
Name: first-package-oistamo
Version: 1.2
Summary: Gaussian and Binomial distributions
Home-page: UNKNOWN
Author: Oistamo Mamadsaidova
Author-email: mamadsaidova.o@gmail.com
License: UNKNOWN
Platform: UNKNOWN
